awrand/__init__.py
awrand/all.py
awrand/config.py
awrand/core.py
awrand-0.0.0.dist-info/LICENSE
awrand-0.0.0.dist-info/METADATA
awrand-0.0.0.dist-info/WHEEL
awrand-0.0.0.dist-info/top_level.txt
awrand-0.0.0.dist-info/RECORD
