Metadata-Version: 2.1
Name: awrand
Version: 0.0.0
Summary: A random generator
Home-page: https://github.com/happyxianyu/awrand
Author: happyxianyu
Author-email: happyxianyu623@outlook.com
License: Apache License 2.0
Platform: UNKNOWN
Requires-Python: >=3.8
